mathlogic/__init__.py
mathlogic/credentials.py
mathlogic/leaderboardutils.py
mathlogic_s3_test-1.1.3.dist-info/METADATA
mathlogic_s3_test-1.1.3.dist-info/WHEEL
mathlogic_s3_test-1.1.3.dist-info/top_level.txt
mathlogic_s3_test-1.1.3.dist-info/RECORD
