Metadata-Version: 2.1
Name: mathlogic-s3-test
Version: 1.1.3
Summary: Python Utilities from MathLogic
Home-page: https://github.com/vermanurag/mathlogic-mathlogic
Author: Anurag Verma
Author-email: anurag.verma@fnmathlogic.com
License: All Rights Reserved
Requires-Dist: pandas
Requires-Dist: jinja2
Requires-Dist: numpy
Requires-Dist: mysql
Requires-Dist: Ipython
